README.md
setup.py
sumko/__init__.py
sumko/check.py
sumko/const.py
sumko/convert.py
sumko/datetime.py
sumko/download.py
sumko/exceptions.py
sumko/file.py
sumko/status_codes.py
sumko/string.py
sumko/test.py
sumko/utils.py
sumko.egg-info/PKG-INFO
sumko.egg-info/SOURCES.txt
sumko.egg-info/dependency_links.txt
sumko.egg-info/top_level.txt
sumko/orm/__init__.py
sumko/tools/__init__.py
sumko/tools/htmltoimage.py
sumko/tools/htmltopdf.py
sumko/tools/sqltocsv.py
sumko/tools/sqltoexcel.py
sumko/tools/sqltopdf.py