Metadata-Version: 2.1
Name: sumko
Version: 1.0.0
Summary: SumKo is a Python microservices framework that lets service developers concentrate on application logic and encourages testability.
Home-page: https://github.com/fovegage/sumko
Author: fovegage
Author-email: fovegage@gmail.com
License: UNKNOWN
Platform: UNKNOWN
Classifier: Programming Language :: Python :: 3
Classifier: License :: OSI Approved :: MIT License
Classifier: Operating System :: OS Independent
